rejex/__init__.py
rejex/rejex_class.py
rejex/rejex_static.py
rejex-0.0.1.1.dist-info/LICENSE
rejex-0.0.1.1.dist-info/METADATA
rejex-0.0.1.1.dist-info/WHEEL
rejex-0.0.1.1.dist-info/top_level.txt
rejex-0.0.1.1.dist-info/RECORD
