Metadata-Version: 2.1
Name: rejex
Version: 0.0.1.1
Summary: Tool used to build regex expressions for python
Home-page: https://github.com/skandabhairava/Rejex
Author: Terroid
Author-email: skandabhairava@gmail.com
License: UNKNOWN
Project-URL: Bug Tracker, https://github.com/skandabhairava/Rejex/issues
Platform: UNKNOWN
Classifier: Programming Language :: Python :: 3
Classifier: License :: OSI Approved :: MIT License
Classifier: Operating System :: OS Independent
Requires-Python: >=3.6
License-File: LICENSE
